pliny/__init__.py
pliny/__main__.py
pliny-0.1.0.dist-info/WHEEL
pliny-0.1.0.dist-info/METADATA
pliny-0.1.0.dist-info/RECORD
