Metadata-Version: 2.1
Name: pliny
Version: 0.1.0
Summary: Pliny web framework (under construction)
Author: Scott Persinger
Author-email: scottpersinger@gmail.com
Requires-Python: >=3.9,<4.0
Classifier: Programming Language :: Python :: 3
Classifier: Programming Language :: Python :: 3.9
Classifier: Programming Language :: Python :: 3.10
Classifier: Programming Language :: Python :: 3.11
Requires-Dist: typer[all] (>=0.9.0,<0.10.0)
